Metadata-Version: 2.1
Name: torchfsdd
Version: 0.1.2
Summary: A utility for wrapping the Free Spoken Digit Dataset into PyTorch-ready data set splits.
Home-page: https://github.com/eonu/torch-fsdd
Author: Edwin Onuonga
Author-email: ed@eonu.net
License: MIT
Project-URL: Documentation, https://torchfsdd.readthedocs.io/en/latest
Project-URL: Bug Tracker, https://github.com/eonu/torch-fsdd/issues
Project-URL: Source Code, https://github.com/eonu/torch-fsdd
Platform: UNKNOWN
Classifier: Development Status :: 4 - Beta
Classifier: Programming Language :: Python :: 3.6
Classifier: Programming Language :: Python :: 3.7
Classifier: Programming Language :: Python :: 3.8
Classifier: Programming Language :: Python :: 3.9
Classifier: License :: OSI Approved :: MIT License
Classifier: Operating System :: Unix
Classifier: Operating System :: MacOS
Classifier: Intended Audience :: Science/Research
Classifier: Topic :: Software Development
Classifier: Topic :: Scientific/Engineering
Classifier: Natural Language :: English
Requires-Python: >=3.6
Provides-Extra: torch
